tests/__init__.py
tests/test_analysis.py
tests/test_graph.py
tests/test_rewriting.py
tex2net/__init__.py
tex2net/analysis.py
tex2net/graph.py
tex2net/rewriting.py
tex2net/visualization.py
tex2net-1.38.dist-info/LICENSE
tex2net-1.38.dist-info/METADATA
tex2net-1.38.dist-info/WHEEL
tex2net-1.38.dist-info/top_level.txt
tex2net-1.38.dist-info/RECORD
