Metadata-Version: 2.1
Name: tex2net
Version: 1.38
Summary: Build character graphs from text.
Author: jtaca
Author-email: jtaca <joaotiagoaparicio@gmail.com>
License: GPL-3
Project-URL: Source, https://github.com/jtaca/tex2net
Project-URL: Tracker, https://github.com/jtaca/tex2net/issues
Keywords: knowledge-graph,NLP,unstructured-data,slm
Classifier: Programming Language :: Python :: 3
Classifier: License :: OSI Approved :: GNU General Public License v3 (GPLv3)
Classifier: Operating System :: OS Independent
Requires-Python: >=3.9
License-File: LICENSE
Requires-Dist: graphviz
Requires-Dist: pyyaml
Requires-Dist: python-docx
Requires-Dist: python-dotenv
Requires-Dist: PyPDF2
Requires-Dist: lxml
Requires-Dist: spacy==3.8.3
Requires-Dist: networkx>=2.0
Requires-Dist: matplotlib>=3.0
Requires-Dist: transformers>=4.0
Requires-Dist: torch
Requires-Dist: pyvis
Requires-Dist: python-louvain
Requires-Dist: pandas
Requires-Dist: sentencepiece
Requires-Dist: typing-extensions
Requires-Dist: numpy<2
